sample/__init__.py
translation_augmentation/__init__.py
translation_augmentation/translation_augmentation.py
translation_augmentation/utilities.py
translation_augmentation-0.7.data/scripts/runner
translation_augmentation-0.7.dist-info/DESCRIPTION.rst
translation_augmentation-0.7.dist-info/METADATA
translation_augmentation-0.7.dist-info/RECORD
translation_augmentation-0.7.dist-info/WHEEL
translation_augmentation-0.7.dist-info/metadata.json
translation_augmentation-0.7.dist-info/top_level.txt
