Metadata-Version: 2.0
Name: translation-augmentation
Version: 0.7
Summary: A python project that augments sentences using neural machine translation.
Home-page: https://github.com/admdemiraj/Text_Augmentation_via_Translation
Author: Admir Demiraj
Author-email: admdemiraj@gmail.com
License: MIT
Keywords: data_augmentation nlp machine_learning text_augmentation translation
Platform: UNKNOWN
Classifier: Programming Language :: Python :: 3.6
Requires-Python: >=3
